functions_by_rusnak/README.md
functions_by_rusnak/math_functions.py
functions_by_rusnak-0.3.0.dist-info/WHEEL
functions_by_rusnak-0.3.0.dist-info/METADATA
functions_by_rusnak-0.3.0.dist-info/RECORD
